app.py
secreteer-0.1.0.dist-info/METADATA
secreteer-0.1.0.dist-info/WHEEL
secreteer-0.1.0.dist-info/licenses/LICENSE
secreteer-0.1.0.dist-info/RECORD
